archive_reader/__init__.py
archive_reader/__main__.py
archive_reader/app.py
archive_reader/archiver.css
archive_reader/core.py
archive_reader/hyperkitty.py
archive_reader/models.py
archive_reader/schemas.py
archive_reader/screens.py
archive_reader/widgets.py
areader-0.1.1.dist-info/METADATA
areader-0.1.1.dist-info/WHEEL
areader-0.1.1.dist-info/entry_points.txt
areader-0.1.1.dist-info/RECORD
