Metadata-Version: 2.1
Name: areader
Version: 0.1.1
Summary: Terminal based archives reader for Hyperkitty, GNU Mailman's archiver
Author-Email: Abhilash Raj <raj.abhilash1@gmail.com>
License: Apache-2.0
Requires-Python: >=3.10
Requires-Dist: textual>=0.30.0
Requires-Dist: httpx
Requires-Dist: marshmallow
Requires-Dist: timeago
Requires-Dist: orm[sqlite]>=0.3.1
Requires-Dist: greenlet>=2.0.2
